fact/__init__.py
fact/fact.py
pymfactorial-0.1.dist-info/LICENSE
pymfactorial-0.1.dist-info/METADATA
pymfactorial-0.1.dist-info/WHEEL
pymfactorial-0.1.dist-info/top_level.txt
pymfactorial-0.1.dist-info/RECORD
