Metadata-Version: 2.1
Name: pymfactorial
Version: 0.1
Summary: pym Factorial module.
Home-page: https://pymbook.readthedocs.io/en/latest/
Author: Kushal Das
Author-email: kushaldas@gmail.com
License: MIT
Platform: Linux
